fpp/__init__.py
fpp/__main__.py
file_plus_plus-1.0.0.dist-info/METADATA
file_plus_plus-1.0.0.dist-info/WHEEL
file_plus_plus-1.0.0.dist-info/top_level.txt
file_plus_plus-1.0.0.dist-info/RECORD
