Metadata-Version: 2.1
Name: file-plus-plus
Version: 1.0.0
Summary: file-plus-plus!!!
